sspm/__init__.py
sspm/plugin.py
sspm/plugin_base.py
sspm/pluginmanager.py
sspm/version.py
test/__init__.py
test/test_all.py
test/test_plugin_manager.py
test/test_settings.py
SSPM-1.2.1.dist-info/LICENSE
SSPM-1.2.1.dist-info/METADATA
SSPM-1.2.1.dist-info/WHEEL
SSPM-1.2.1.dist-info/top_level.txt
SSPM-1.2.1.dist-info/RECORD
