Metadata-Version: 2.1
Name: SSPM
Version: 1.2.1
Summary: SSPM simple plugin manger based on YAPSY
Home-page: https://gitlab.com/stevencnix/sspm
Download-URL: https://gitlab.com/stevencnix/sspm/-/archive/v1.2.1/sspm-v1.2.1.tar.gz
Author: Steven Nix
Author-email: stevencnix@gmail.com
License: GNU LGPLv3
Classifier: Operating System :: OS Independent
Classifier: Intended Audience :: Developers
Classifier: License :: OSI Approved :: GNU Lesser General Public License v3 (LGPLv3)
Classifier: Programming Language :: Python :: 3.8
Classifier: Programming Language :: Python :: 3.10
Requires-Python: >=3.8
License-File: LICENSE
